odoo9_addon_stock_auto_move-9.0.1.0.0.99.dev14-py2.7-nspkg.pth
odoo9_addon_stock_auto_move-9.0.1.0.0.99.dev14.dist-info/METADATA
odoo9_addon_stock_auto_move-9.0.1.0.0.99.dev14.dist-info/RECORD
odoo9_addon_stock_auto_move-9.0.1.0.0.99.dev14.dist-info/WHEEL
odoo9_addon_stock_auto_move-9.0.1.0.0.99.dev14.dist-info/namespace_packages.txt
odoo9_addon_stock_auto_move-9.0.1.0.0.99.dev14.dist-info/top_level.txt
odoo_addons/stock_auto_move/README.rst
odoo_addons/stock_auto_move/__init__.py
odoo_addons/stock_auto_move/__openerp__.py
odoo_addons/stock_auto_move/data/stock_auto_move_data.xml
odoo_addons/stock_auto_move/demo/stock_auto_move_demo.xml
odoo_addons/stock_auto_move/i18n/ca.po
odoo_addons/stock_auto_move/i18n/de.po
odoo_addons/stock_auto_move/i18n/es.po
odoo_addons/stock_auto_move/i18n/es_AR.po
odoo_addons/stock_auto_move/i18n/es_MX.po
odoo_addons/stock_auto_move/i18n/fi.po
odoo_addons/stock_auto_move/i18n/fr.po
odoo_addons/stock_auto_move/i18n/hr.po
odoo_addons/stock_auto_move/i18n/it.po
odoo_addons/stock_auto_move/i18n/pt.po
odoo_addons/stock_auto_move/i18n/pt_BR.po
odoo_addons/stock_auto_move/i18n/pt_PT.po
odoo_addons/stock_auto_move/i18n/ro.po
odoo_addons/stock_auto_move/i18n/sl.po
odoo_addons/stock_auto_move/i18n/stock_auto_move.pot
odoo_addons/stock_auto_move/i18n/tr.po
odoo_addons/stock_auto_move/i18n/tr_TR.po
odoo_addons/stock_auto_move/i18n/zh_CN.po
odoo_addons/stock_auto_move/models/__init__.py
odoo_addons/stock_auto_move/models/procurement_order.py
odoo_addons/stock_auto_move/models/procurement_rule.py
odoo_addons/stock_auto_move/models/stock_location_path.py
odoo_addons/stock_auto_move/models/stock_move.py
odoo_addons/stock_auto_move/models/stock_picking.py
odoo_addons/stock_auto_move/static/description/icon.png
odoo_addons/stock_auto_move/tests/__init__.py
odoo_addons/stock_auto_move/tests/test_stock_auto_move.py
odoo_addons/stock_auto_move/views/procurement_rule.xml
odoo_addons/stock_auto_move/views/stock_location_path.xml
odoo_addons/stock_auto_move/views/stock_move.xml
